[
  {
    "_id": "00",
    "day": "Monday",
    "workout": [
      { "title": "Open WOD Beginner", "time": "18:00 - 19:00", "_id": "00" },
      { "title": "Open WOD Basic", "time": "19:15 - 20:15", "_id": "01" }
    ]
  },
  {
    "_id": "01",
    "day": "Tuesday",
    "workout": [
      { "title": "Open WOD Endurance", "time": "18:00 - 19:00", "_id": "02" },
      { "title": "Gymnastic", "time": "19:15 - 20:15", "_id": "03" }
    ]
  },

  {
    "_id": "02",
    "day": "Wednesday",
    "workout": [
      { "title": "Open WOD Beginner", "time": "18:00 - 19:00", "_id": "04" },
      { "title": "Open WOD Basic", "time": "19:15 - 20:15", "_id": "05" }
    ]
  },
  {
    "_id": "03",
    "day": "Thursday",
    "workout": [
      { "title": "Open WOD Team", "time": "18:00 - 19:00", "_id": "06" },
      { "title": "Open WOD Endurance", "time": "19:15 - 20:15", "_id": "07" }
    ]
  },
  {
    "_id": "04",
    "day": "Friday",
    "workout": [
      { "title": "Open WOD Beginner", "time": "18:00 - 19:00", "_id": "08" },
      { "title": "Open WOD Basic", "time": "19:15 - 20:15", "_id": "09" }
    ]
  }
]
